Metadata-Version: 1.1
Name: django-custard
Version: 0.9
Summary: Django runtime typed custom fields for any model.
Home-page: https://github.com/kunitoki/django-custard
Author: Lucio Asnaghi (aka kunitoki)
Author-email: kunitoki@gmail0.9com
License: MIT
Download-URL: https://pypi.python.org/pypi/django-custard
Keywords: django,models,fields,custom,admin,content types
Platform: UNKNOWN
Classifier: Development Status :: 4 - Beta
Classifier: Framework :: Django
Classifier: License :: OSI Approved :: MIT License
Classifier: Intended Audience :: Developers
Classifier: Operating System :: OS Independent
Classifier: Programming Language :: Python
Classifier: Programming Language :: Python :: 2.7
Classifier: Programming Language :: Python :: 3.2
Classifier: Programming Language :: Python :: 3.3
Classifier: Programming Language :: Python :: 3.4
Classifier: Environment :: Web Environment
Classifier: Topic :: Software Development
